<?xml version="1.0" encoding="utf-8"?>
<GenericAutoCrafterDataEntry xmlns:xsi="http://www.w3.org/2001/XMLSchema-instance" xmlns:xsd="http://www.w3.org/2001/XMLSchema">
	<FriendlyName>Crystal Growth Chamber</FriendlyName>
	<SpawnObject>PlasmaHeadCharger</SpawnObject>
	<Value>Vici.CrystalGrowthChamber</Value>
			
	<PowerUsePerSecond>1000</PowerUsePerSecond>  <!-- optional -->
	<PowerTransferPerSecond>1200</PowerTransferPerSecond>  <!-- optional -->
	<MaxPowerStorage>10000</MaxPowerStorage>  <!-- optional -->
	<CraftingString>Converting to</CraftingString>
	<CraftTime>100</CraftTime>
	<OptionalIngredients>false</OptionalIngredients>  <!-- optional -->
	<Recipe>
		<Key>SugaliteCrystal</Key>
		<CraftedKey>SugaliteCrystal</CraftedKey>
		<CraftedAmount>1</CraftedAmount>
		<Costs>
			<CraftCost>
				<Key>Vici.CrystalGrowthMatrix</Key>
				<Amount>1</Amount>
			</CraftCost>
		</Costs>
		<Description>Spend power to convert a Crystal Growth Matrix into a Sugalite Crystal</Description>
	</Recipe>
</GenericAutoCrafterDataEntry>